pyldplayer2/__init__.py
pyldplayer2/base/enums/__init__.py
pyldplayer2/base/enums/console.py
pyldplayer2/base/models/kmp.py
pyldplayer2/base/models/leidian_config.py
pyldplayer2/base/models/leidians_config.py
pyldplayer2/base/models/list2meta.py
pyldplayer2/base/models/record.py
pyldplayer2/base/models/smp.py
pyldplayer2/base/objects/appattr.py
pyldplayer2/base/objects/iconsole.py
pyldplayer2/base/objects/pathcache.py
pyldplayer2/base/utils/__init__.py
pyldplayer2/base/utils/dotDict.py
pyldplayer2/base/utils/subproc.py
pyldplayer2/base/utils/wnd.py
pyldplayer2/base/utils/wndlayout.py
pyldplayer2/coms/batchConsole.py
pyldplayer2/coms/cliCompat.py
pyldplayer2/coms/console.py
pyldplayer2/coms/instanceQuery.py
pyldplayer2/coms/kmpFile.py
pyldplayer2/coms/leidianFile.py
pyldplayer2/coms/recordFile.py
pyldplayer2/coms/smpFile.py
pyldplayer2/coms/wndInstance.py
pyldplayer2/coms/cli/__init__.py
pyldplayer2/coms/cli/consoleCmds.py
pyldplayer2/coms/cli/layout.py
pyldplayer2/utils/discover.py
pyldplayer2/utils/wndlayout.py
pyldplayer2-0.1.0.dist-info/METADATA
pyldplayer2-0.1.0.dist-info/WHEEL
pyldplayer2-0.1.0.dist-info/entry_points.txt
pyldplayer2-0.1.0.dist-info/licenses/LICENSE
pyldplayer2-0.1.0.dist-info/RECORD
