Metadata-Version: 2.4
Name: pyldplayer2
Version: 0.1.0
Summary: pyldplayer2 is a revamped version of the pyldplayer project
Author-email: ZackaryW <36378555+ZackaryW@users.noreply.github.com>
License-File: LICENSE
Requires-Python: >=3.8
Provides-Extra: all
Requires-Dist: psutil>=7.0.0; extra == 'all'
Requires-Dist: pyautogui>=0.9.54; extra == 'all'
Requires-Dist: pygetwindow>=0.0.9; extra == 'all'
Requires-Dist: screeninfo>=0.8.1; extra == 'all'
Requires-Dist: tabulate>=0.9.0; extra == 'all'
Provides-Extra: auto
Requires-Dist: pyautogui>=0.9.54; extra == 'auto'
Requires-Dist: pygetwindow>=0.0.9; extra == 'auto'
Provides-Extra: discover
Requires-Dist: psutil>=7.0.0; extra == 'discover'
Requires-Dist: pygetwindow>=0.0.9; extra == 'discover'
Provides-Extra: shell
Requires-Dist: click>=8.2.0; extra == 'shell'
Requires-Dist: tabulate>=0.9.0; extra == 'shell'
Provides-Extra: wnd
Requires-Dist: pyautogui>=0.9.54; extra == 'wnd'
Requires-Dist: pygetwindow>=0.0.9; extra == 'wnd'
Requires-Dist: screeninfo>=0.8.1; extra == 'wnd'
